pulumi_alicloud/__init__.py
pulumi_alicloud/_inputs.py
pulumi_alicloud/_utilities.py
pulumi_alicloud/get_account.py
pulumi_alicloud/get_caller_identity.py
pulumi_alicloud/get_file_crc64_checksum.py
pulumi_alicloud/get_msc_sub_contact_verification_message.py
pulumi_alicloud/get_msc_sub_contacts.py
pulumi_alicloud/get_msc_sub_subscriptions.py
pulumi_alicloud/get_msc_sub_webhooks.py
pulumi_alicloud/get_regions.py
pulumi_alicloud/get_zones.py
pulumi_alicloud/msc_sub_contract.py
pulumi_alicloud/msc_sub_subscription.py
pulumi_alicloud/msc_sub_webhook.py
pulumi_alicloud/outputs.py
pulumi_alicloud/provider.py
pulumi_alicloud/pulumi-plugin.json
pulumi_alicloud/py.typed
pulumi_alicloud/ackone/__init__.py
pulumi_alicloud/ackone/_inputs.py
pulumi_alicloud/ackone/cluster.py
pulumi_alicloud/ackone/membership_attachment.py
pulumi_alicloud/ackone/outputs.py
pulumi_alicloud/actiontrail/__init__.py
pulumi_alicloud/actiontrail/get_consumer_groups.py
pulumi_alicloud/actiontrail/get_global_events_storage_region.py
pulumi_alicloud/actiontrail/get_history_delivery_jobs.py
pulumi_alicloud/actiontrail/get_instances.py
pulumi_alicloud/actiontrail/get_sasl_acls.py
pulumi_alicloud/actiontrail/get_sasl_users.py
pulumi_alicloud/actiontrail/get_topics.py
pulumi_alicloud/actiontrail/get_trails.py
pulumi_alicloud/actiontrail/get_trails_deprecated.py
pulumi_alicloud/actiontrail/global_events_storage_region.py
pulumi_alicloud/actiontrail/history_delivery_job.py
pulumi_alicloud/actiontrail/outputs.py
pulumi_alicloud/actiontrail/trail.py
pulumi_alicloud/actiontrail/trail_deprecated.py
pulumi_alicloud/adb/__init__.py
pulumi_alicloud/adb/_inputs.py
pulumi_alicloud/adb/account.py
pulumi_alicloud/adb/backup_policy.py
pulumi_alicloud/adb/cluster.py
pulumi_alicloud/adb/connection.py
pulumi_alicloud/adb/db_cluster.py
pulumi_alicloud/adb/db_cluster_lake_version.py
pulumi_alicloud/adb/get_clusters.py
pulumi_alicloud/adb/get_db_cluster_lake_versions.py
pulumi_alicloud/adb/get_db_clusters.py
pulumi_alicloud-3.75.0.dist-info/METADATA
pulumi_alicloud-3.75.0.dist-info/WHEEL
pulumi_alicloud-3.75.0.dist-info/top_level.txt
pulumi_alicloud-3.75.0.dist-info/RECORD
